[
  {
    "id": "55ea513f-adf1-48a7-88ec-0ee9c50834c9",
    "creator_id": "",
    "name": "Fia & Shell wedding wishlist",
    "target_amount": 513.11,
    "total_raised": 400,
    "description": "",
    "thank_you_message": "",
    "category": "wedding",
    "visibility": "",
    "cover_image": "",
    "createdAt": "",
    "updatedAt": "",
    "archived": false,
    "deleted": false,
    "items": [
      {
        "id": "1",
        "name": "CUISINART 15 Piece Stainless Steel Hollow Handle Block Set",
        "description": "",
        "price": 124.15,
        "quantity_requested": 1,
        "picture": "https://res.cloudinary.com/drnmh0rkc/image/upload/v1741289947/popular%20items/qc66y0rlpqng9svohtvt.png"
      },
      {
        "id": "2",
        "name": "Ninja BL660C Professional Countertop Blender",
        "description": "",
        "price": 149.98,
        "quantity_requested": 1,
        "picture": "https://res.cloudinary.com/drnmh0rkc/image/upload/v1741289947/popular%20items/erc2pmkmyuttrcqvic4x.png"
      },
      {
        "id": "3",
        "name": "Braun MQ505 Portable Immersion Hand Blender",
        "description": "",
        "price": 79.98,
        "quantity_requested": 1,
        "picture": "https://res.cloudinary.com/drnmh0rkc/image/upload/v1741289947/popular%20items/avgwwibs8xm54sjsijcb.png"
      },
      {
        "id": "4",
        "name": "Fujifilm Instax Square SQ1 Instant Camera",
        "description": "",
        "price": 159,
        "quantity_requested": 1,
        "picture": "https://res.cloudinary.com/drnmh0rkc/image/upload/v1741289947/popular%20items/k53m43bgbgohkg9erewp.png"
      }
    ]
  },
  {
    "id": "8a826cee-2c47-4e14-a853-beb6c5e1646e",
    "creator_id": "",
    "name": "Stella & Mike wedding wishlist",
    "target_amount": 504.96,
    "total_raised": 320,
    "description": "",
    "thank_you_message": "",
    "category": "wedding",
    "visibility": "",
    "cover_image": "",
    "createdAt": "",
    "updatedAt": "",
    "archived": false,
    "deleted": false,
    "items": [
      {
        "id": "5",
        "name": "KitchenAid Artisan Series 5-Quart Tilt-Head Stand Mixer",
        "description": "",
        "price": 429.98,
        "quantity_requested": 1,
        "picture": "https://res.cloudinary.com/drnmh0rkc/image/upload/v1741289947/popular%20items/brsc8rmfb1qwxmgrmyny.png"
      },
      {
        "id": "6",
        "name": "Cuisinart Salad Spinner with Easy-to-Spin Knob",
        "description": "",
        "price": 24.99,
        "quantity_requested": 1,
        "picture": "https://res.cloudinary.com/drnmh0rkc/image/upload/v1741289947/popular%20items/i1hklhff4p7e8rrk5kp7.png"
      },
      {
        "id": "7",
        "name": "Utopia Bedding Bed Pillows for Sleeping Queen Size",
        "description": "",
        "price": 39.99,
        "quantity_requested": 1,
        "picture": "https://res.cloudinary.com/drnmh0rkc/image/upload/v1741289947/popular%20items/bffgaxcazatxnjhfkfj9.png"
      },
      {
        "id": "8",
        "name": "jelly cat",
        "description": "",
        "price": 10,
        "quantity_requested": 1,
        "picture": ""
      }
    ]
  },
  {
    "id": "91fd2c8e-aaea-4940-ba39-d5d91e131276",
    "creator_id": "",
    "name": "Joe & Lucy wedding wishlist",
    "target_amount": 647.18,
    "total_raised": 600,
    "description": "",
    "thank_you_message": "",
    "category": "wedding",
    "visibility": "",
    "cover_image": "",
    "createdAt": "",
    "updatedAt": "",
    "archived": false,
    "deleted": false,
    "items": [
      {
        "id": "9",
        "name": "Ninja Foodi 6-in-1 8-qt. (7.6L) 2-Basket Air Fryer",
        "description": "",
        "price": 179.99,
        "quantity_requested": 1,
        "picture": "https://res.cloudinary.com/drnmh0rkc/image/upload/v1741289947/popular%20items/xfvvjuvphv0rkt3oisfq.png"
      },
      {
        "id": "10",
        "name": "Instant Pot Duo 7-in-1 Electric Pressure Cooker, Slow Cooker",
        "description": "",
        "price": 175.95,
        "quantity_requested": 1,
        "picture": "https://res.cloudinary.com/drnmh0rkc/image/upload/v1741289947/popular%20items/ovsbuvw0pbtmjls9fvui.png"
      },
      {
        "id": "11",
        "name": "Hamilton Beach Electric Panini Press Grill with Locking Lid",
        "description": "",
        "price": 123,
        "quantity_requested": 1,
        "picture": "https://res.cloudinary.com/drnmh0rkc/image/upload/v1741289947/popular%20items/e4peujba05qarnwbxjgp.png"
      },
      {
        "id": "12",
        "name": "LEVOIT Air Purifiers for Bedroom Home",
        "description": "",
        "price": 139.99,
        "quantity_requested": 1,
        "picture": "https://res.cloudinary.com/drnmh0rkc/image/upload/v1741289947/popular%20items/mksjk2smu021loy1kpu6.png"
      },
      {
        "id": "13",
        "name": "Embroidered Couples Hoodie Matching Couples Date Hoodie",
        "description": "",
        "price": 28.25,
        "quantity_requested": 1,
        "picture": ""
      }
    ]
  },
  {
    "id": "6f409a0b-1dfd-4fc4-8487-7f06d689be72",
    "creator_id": "",
    "name": "Ada New Home wishlist",
    "target_amount": 992.08,
    "total_raised": 480,
    "description": "",
    "thank_you_message": "",
    "category": "event",
    "visibility": "",
    "cover_image": "",
    "createdAt": "",
    "updatedAt": "",
    "archived": false,
    "deleted": false,
    "items": [
      {
        "id": "14",
        "name": "Dyson V8 Origin Plus Cordless Vacuum",
        "description": "",
        "price": 492.09,
        "quantity_requested": 1,
        "picture": "https://res.cloudinary.com/drnmh0rkc/image/upload/v1741289947/popular%20items/rnlipxobi02sikhxzlgf.png"
      },
      {
        "id": "15",
        "name": "Dyson AM07 White - Fan",
        "description": "",
        "price": 499.99,
        "quantity_requested": 1,
        "picture": "https://res.cloudinary.com/drnmh0rkc/image/upload/v1741289947/popular%20items/hzqxlaiw4yy8clll96os.png"
      }
    ]
  },
  {
    "id": "b86a1a52-c357-4d26-a757-9a91017a0e98",
    "creator_id": "",
    "name": "Charles birthday wishlist",
    "target_amount": 1596.9,
    "total_raised": 990,
    "description": "",
    "thank_you_message": "",
    "category": "event",
    "visibility": "",
    "cover_image": "",
    "createdAt": "",
    "updatedAt": "",
    "archived": false,
    "deleted": false,
    "items": [
      {
        "id": "16",
        "name": "Stand Mixer",
        "description": "",
        "price": 429.98,
        "quantity_requested": 1,
        "picture": ""
      },
      {
        "id": "17",
        "name": "Ninja Air Fryer",
        "description": "",
        "price": 179.99,
        "quantity_requested": 1,
        "picture": ""
      },
      {
        "id": "18",
        "name": "Toaster ",
        "description": "",
        "price": 54.99,
        "quantity_requested": 1,
        "picture": ""
      },
      {
        "id": "19",
        "name": "Front Door Mat ",
        "description": "",
        "price": 26.52,
        "quantity_requested": 1,
        "picture": ""
      },
      {
        "id": "20",
        "name": "Large Cylindric Ribbed Candle",
        "description": "",
        "price": 29.34,
        "quantity_requested": 1,
        "picture": "https://res.cloudinary.com/drnmh0rkc/image/upload/v1741295294/popular%20items/hpqltfztrs9os01wbe9x.png"
      },
      {
        "id": "21",
        "name": "Coffee Grinder",
        "description": "",
        "price": 29.99,
        "quantity_requested": 1,
        "picture": ""
      },
      {
        "id": "22",
        "name": "Keurig K-Duo Coffee Maker",
        "description": "",
        "price": 177.21,
        "quantity_requested": 1,
        "picture": ""
      },
      {
        "id": "23",
        "name": "Marshall Bluetooth Speaker",
        "description": "",
        "price": 368.89,
        "quantity_requested": 1,
        "picture": ""
      },
      {
        "id": "24",
        "name": "Ninja NC501 CREAMi Deluxe Ice Cream & Frozen Treat Maker",
        "description": "",
        "price": 299.99,
        "quantity_requested": 1,
        "picture": ""
      }
    ]
  },
  {
    "id": "937f13ce-12b7-4851-9616-bd2b2914f74e",
    "creator_id": "",
    "name": "Kiana birthday wishlist",
    "target_amount": 899,
    "total_raised": 230,
    "description": "",
    "thank_you_message": "",
    "category": "event",
    "visibility": "",
    "cover_image": "",
    "createdAt": "",
    "updatedAt": "",
    "archived": false,
    "deleted": false,
    "items": [
      {
        "id": "25",
        "name": "iphone 16e",
        "description": "",
        "price": 899,
        "quantity_requested": 1,
        "picture": ""
      }
    ]
  },
  {
    "id": "3e71fc9e-e441-497f-a897-abe8fafad3f1",
    "creator_id": "",
    "name": "James & Beth honeymoon wishlist",
    "target_amount": 8000,
    "total_raised": 6800,
    "description": "",
    "thank_you_message": "",
    "category": "honeymoon",
    "visibility": "",
    "cover_image": "",
    "createdAt": "",
    "updatedAt": "",
    "archived": false,
    "deleted": false,
    "items": [
      {
        "id": "26",
        "name": "flight ticket to japan",
        "description": "",
        "price": 4000,
        "quantity_requested": 2,
        "picture": ""
      }
    ]
  },
  {
    "id": "31d5136d-7808-4f14-a6a7-1d3a6303cfd0",
    "creator_id": "",
    "name": "Max baby registry wishlist",
    "target_amount": 4000,
    "total_raised": 2680,
    "description": "baby",
    "thank_you_message": "",
    "category": "baby",
    "visibility": "",
    "cover_image": "",
    "createdAt": "",
    "updatedAt": "",
    "archived": false,
    "deleted": false,
    "items": [
      {
        "id": "1",
        "name": "crib",
        "description": "",
        "price": 300,
        "quantity_requested": 1,
        "picture": ""
      },
      {
        "id": "50",
        "name": "infant formula ",
        "description": "",
        "price": 50,
        "quantity_requested": 10,
        "picture": ""
      },
      {
        "id": "51",
        "name": "diapers and wipes",
        "description": "",
        "price": 100,
        "quantity_requested": 1,
        "picture": ""
      },
      {
        "id": "52",
        "name": "medical and first aid kit ",
        "description": "",
        "price": 100,
        "quantity_requested": 1,
        "picture": ""
      },
      {
        "id": "53",
        "name": "emergency medical fund",
        "description": "",
        "price": 3000,
        "quantity_requested": 1,
        "picture": ""
      }
    ]
  },
  {
    "id": "1aca3b9b-96ab-4df7-a48d-f5eb6804a382",
    "creator_id": "",
    "name": "Josh baby registry wishlist",
    "target_amount": 982.19,
    "total_raised": 900,
    "description": "",
    "thank_you_message": "",
    "category": "baby",
    "visibility": "",
    "cover_image": "",
    "createdAt": "",
    "updatedAt": "",
    "archived": false,
    "deleted": false,
    "items": [
      {
        "id": "8",
        "name": "A High Contrast Book For Newborns ",
        "description": "",
        "price": 13.5,
        "quantity_requested": 1,
        "picture": ""
      },
      {
        "id": "9",
        "name": "Mr. Brown Can Moo! Can You?: Dr. Seuss's Book of Wonderful Noises",
        "description": "",
        "price": 17.47,
        "quantity_requested": 1,
        "picture": "https://res.cloudinary.com/drnmh0rkc/image/upload/v1741303211/popular%20items/xz4cqd6p4ebgj61pulvt.png"
      },
      {
        "id": "10",
        "name": "Sudocrem - Diaper Rash Cream for Baby",
        "description": "",
        "price": 14.97,
        "quantity_requested": 1,
        "picture": "https://res.cloudinary.com/drnmh0rkc/image/upload/v1741303211/popular%20items/xqyhmusvrpumozvlc0mr.png"
      },
      {
        "id": "54",
        "name": "Wall Nanny - Baby Gate Wall Protector",
        "description": "",
        "price": 19.95,
        "quantity_requested": 1,
        "picture": "https://res.cloudinary.com/drnmh0rkc/image/upload/v1741303212/popular%20items/izfayx3epafg7zrraomv.png"
      },
      {
        "id": "55",
        "name": "Toddler Name Puzzle Wooden Personalized Gift",
        "description": "",
        "price": 24.96,
        "quantity_requested": 1,
        "picture": "https://res.cloudinary.com/drnmh0rkc/image/upload/v1741303210/popular%20items/holjzo8jjhoyn1o6nngq.png"
      },
      {
        "id": "56",
        "name": "Musical Wooden Ballerina Carousel Keepsake",
        "description": "",
        "price": 24.84,
        "quantity_requested": 1,
        "picture": "https://res.cloudinary.com/drnmh0rkc/image/upload/v1741303210/popular%20items/uqi669firmrvruf9108z.png"
      },
      {
        "id": "57",
        "name": "Animal Crochet Baby Rattle, Baby Shower Gift",
        "description": "",
        "price": 27.16,
        "quantity_requested": 1,
        "picture": "https://res.cloudinary.com/drnmh0rkc/image/upload/v1741303210/popular%20items/mlpjj9hogcgexvbnatxe.png"
      },
      {
        "id": "58",
        "name": "Baby Signs: A Baby-Sized Introduction to Speaking with Sign Language",
        "description": "",
        "price": 34.99,
        "quantity_requested": 1,
        "picture": "https://res.cloudinary.com/drnmh0rkc/image/upload/v1741303211/popular%20items/gokxmurcly0jamktrn8g.png"
      },
      {
        "id": "59",
        "name": "The Complete Baby and Toddler Cookbook",
        "description": "",
        "price": 35.99,
        "quantity_requested": 1,
        "picture": "https://res.cloudinary.com/drnmh0rkc/image/upload/v1741303212/popular%20items/pqlcihwmpdblbpqurl5f.png"
      },
      {
        "id": "60",
        "name": "bodysuit",
        "description": "",
        "price": 54.27,
        "quantity_requested": 1,
        "picture": ""
      },
      {
        "id": "61",
        "name": "WaterWipes Plastic-Free Original Baby Wipes",
        "description": "",
        "price": 57,
        "quantity_requested": 1,
        "picture": ""
      },
      {
        "id": "62",
        "name": " Soother Toy",
        "description": "",
        "price": 79.99,
        "quantity_requested": 1,
        "picture": ""
      },
      {
        "id": "63",
        "name": "Graco Hadley 4-in-1 Convertible Crib with Drawer",
        "description": "",
        "price": 376,
        "quantity_requested": 1,
        "picture": "https://res.cloudinary.com/drnmh0rkc/image/upload/v1741303212/popular%20items/cjtwsitz2fonjgj3rw2e.png"
      },
      {
        "id": "64",
        "name": "cctv",
        "description": "",
        "price": 100,
        "quantity_requested": 1,
        "picture": ""
      },
      {
        "id": "65",
        "name": "Building Block Set 24 pcs Wooden Construction Set",
        "description": "",
        "price": 101.1,
        "quantity_requested": 1,
        "picture": ""
      }
    ]
  },

  {
    "id": "30c41ba5-d7da-4403-8af6-765771ecdae9",
    "creator_id": "",
    "name": "Charles's baby registry wishlist",
    "target_amount": 251.77,
    "total_raised": 50,
    "description": "",
    "thank_you_message": "",
    "category": "baby",
    "visibility": "",
    "cover_image": "",
    "createdAt": "",
    "updatedAt": "",
    "archived": false,
    "deleted": false,
    "items": [
      {
        "id": "31",
        "name": "Mom Bracelet with Kids Names: Engraved Charm Bracelet",
        "description": "",
        "price": 44.26,
        "quantity_requested": 1,
        "picture": "https://res.cloudinary.com/drnmh0rkc/image/upload/v1741303213/popular%20items/kloc0qtl5rhlm8lm6gu2.png"
      },
      {
        "id": "32",
        "name": "Personalised Bamboo Childrens Dining Set Spoon & Bowl",
        "description": "",
        "price": 58.26,
        "quantity_requested": 1,
        "picture": "https://res.cloudinary.com/drnmh0rkc/image/upload/v1741303213/popular%20items/ea2jo67sgmkvqlhfsdrx.png"
      },
      {
        "id": "33",
        "name": "Dr. Brown's Natural Flow Anti-Colic Options+ Narrow Baby Bottle, 4 pack",
        "description": "",
        "price": 34.99,
        "quantity_requested": 1,
        "picture": "https://res.cloudinary.com/drnmh0rkc/image/upload/v1741303212/popular%20items/toyxj9qfuszuzmjpx8g9.png"
      },
      {
        "id": "34",
        "name": "Sudocrem - Diaper Rash Cream for Baby",
        "description": "",
        "price": 14.97,
        "quantity_requested": 1,
        "picture": "https://res.cloudinary.com/drnmh0rkc/image/upload/v1741303211/popular%20items/xqyhmusvrpumozvlc0mr.png"
      },
      {
        "id": "35",
        "name": "OXO Tot Bottle Drying Rack",
        "description": "",
        "price": 39.99,
        "quantity_requested": 1,
        "picture": "https://res.cloudinary.com/drnmh0rkc/image/upload/v1741303211/popular%20items/vszgf0c5izkxlibsotfk.png"
      },
      {
        "id": "36",
        "name": "Soft Plush Fox Baby Blanket for Boys Girls Nursery Unisex",
        "description": "",
        "price": 21.99,
        "quantity_requested": 1,
        "picture": "https://res.cloudinary.com/drnmh0rkc/image/upload/v1741303211/popular%20items/lusddbk7inwkinrg454r.png"
      },
      {
        "id": "37",
        "name": "Personalized Baby Shower Gift Basket",
        "description": "",
        "price": 37.31,
        "quantity_requested": 1,
        "picture": "https://res.cloudinary.com/drnmh0rkc/image/upload/v1741303210/popular%20items/q8bmm8ymtg9usst10lov.png"
      }
    ]
  },
  {
    "id": "d753a553-6293-4840-9558-da2e8eb38957",
    "creator_id": "",
    "name": "Luna's baby registry",
    "target_amount": 1926.28,
    "total_raised": 1500,
    "description": "",
    "thank_you_message": "",
    "category": "baby",
    "visibility": "",
    "cover_image": "",
    "createdAt": "",
    "updatedAt": "",
    "archived": false,
    "deleted": false,
    "items": [
      {
        "id": "38",
        "name": "Aveeno Baby Daily Bath Time Solutions Gift Set To Prevent Dry Skin",
        "description": "",
        "price": 59.99,
        "quantity_requested": 1,
        "picture": "https://res.cloudinary.com/drnmh0rkc/image/upload/v1741303212/popular%20items/filk7atztnm7aev3ec56.png"
      },
      {
        "id": "39",
        "name": "Graco FastAction Jogger LX Stroller, Drive",
        "description": "",
        "price": 449.97,
        "quantity_requested": 1,
        "picture": "https://res.cloudinary.com/drnmh0rkc/image/upload/v1741303212/popular%20items/htb7gexyi0imwvk5zxs9.png"
      },
      {
        "id": "40",
        "name": "Soft Plush Fox Baby Blanket for Boys Girls Nursery Unisex",
        "description": "",
        "price": 21.99,
        "quantity_requested": 1,
        "picture": "https://res.cloudinary.com/drnmh0rkc/image/upload/v1741303211/popular%20items/lusddbk7inwkinrg454r.png"
      },
      {
        "id": "41",
        "name": "Dr. Brown's Natural Flow Anti-Colic Options+ Narrow Baby Bottle, 4 pack",
        "description": "",
        "price": 34.99,
        "quantity_requested": 1,
        "picture": "https://res.cloudinary.com/drnmh0rkc/image/upload/v1741303212/popular%20items/toyxj9qfuszuzmjpx8g9.png"
      },
      {
        "id": "42",
        "name": "Personalized embroidered sweater chunky knit oversized fit",
        "description": "",
        "price": 53.44,
        "quantity_requested": 1,
        "picture": "https://res.cloudinary.com/drnmh0rkc/image/upload/v1741303210/popular%20items/bbxkwoi38hocgktjvust.png"
      },
      {
        "id": "43",
        "name": "Summer Infant Baby Pixel Zoom HD Video Baby Monitor with 5-Inch Display and Remote Steering Camera",
        "description": "",
        "price": 280.2,
        "quantity_requested": 1,
        "picture": "https://res.cloudinary.com/drnmh0rkc/image/upload/v1741303212/popular%20items/fohmf6fu6pwtkcqfymxp.png"
      },
      {
        "id": "44",
        "name": "Graco Hadley 4-in-1 Convertible Crib with Drawer",
        "description": "",
        "price": 376,
        "quantity_requested": 1,
        "picture": "https://res.cloudinary.com/drnmh0rkc/image/upload/v1741303212/popular%20items/cjtwsitz2fonjgj3rw2e.png"
      },
      {
        "id": "45",
        "name": "diaper ",
        "description": "",
        "price": 29.97,
        "quantity_requested": 5,
        "picture": ""
      },
      {
        "id": "46",
        "name": "toddler nutritional drink ",
        "description": "",
        "price": 69.97,
        "quantity_requested": 5,
        "picture": ""
      },
      {
        "id": "47",
        "name": "baby toys",
        "description": "",
        "price": 100,
        "quantity_requested": 1,
        "picture": ""
      },
      {
        "id": "48",
        "name": "baby food",
        "description": "",
        "price": 5,
        "quantity_requested": 10,
        "picture": ""
      }
    ]
  },
  {
    "id": "757092cb-a0f2-4a9c-ab37-1ceeb10d637d",
    "creator_id": "",
    "name": "Help my son Zach Baby Medical wishlist",
    "target_amount": 10000,
    "total_raised": 3800,
    "description": "",
    "thank_you_message": "",
    "category": "baby",
    "visibility": "",
    "cover_image": "",
    "createdAt": "",
    "updatedAt": "",
    "archived": false,
    "deleted": false,
    "items": [
      {
        "id": "49",
        "name": "medical expense ",
        "description": "",
        "price": 10000,
        "quantity_requested": 1,
        "picture": ""
      }
    ]
  },
  {
    "id": "c2779e26-6be3-4d81-b7fa-02464b02cb99",
    "creator_id": "",
    "name": "Ruby's baby medical wishlist",
    "target_amount": 3000,
    "total_raised": 1000,
    "description": "",
    "thank_you_message": "",
    "category": "baby",
    "visibility": "",
    "cover_image": "",
    "createdAt": "",
    "updatedAt": "",
    "archived": false,
    "deleted": false,
    "items": [
      {
        "id": "66",
        "name": "doctor visit ",
        "description": "",
        "price": 2000,
        "quantity_requested": 1,
        "picture": ""
      },
      {
        "id": "67",
        "name": "baby first year medical fund",
        "description": "",
        "price": 1000,
        "quantity_requested": 1,
        "picture": ""
      }
    ]
  },
  {
    "id": "a4bdc3cc-1f38-4c87-9985-91509e2a31c1",
    "creator_id": "",
    "name": "Somi baby registry wishlist",
    "target_amount": 330,
    "total_raised": 150,
    "description": "",
    "thank_you_message": "",
    "category": "baby",
    "visibility": "",
    "cover_image": "",
    "createdAt": "",
    "updatedAt": "",
    "archived": false,
    "deleted": false,
    "items": [
      {
        "id": "68",
        "name": " Newborn Onesies & Pajamas",
        "description": "",
        "price": 50,
        "quantity_requested": 5,
        "picture": ""
      },
      {
        "id": "69",
        "name": " Bibs, Socks, & Hats Set ",
        "description": "",
        "price": 30,
        "quantity_requested": 1,
        "picture": ""
      },
      {
        "id": "70",
        "name": " Special Occasion Outfit ",
        "description": "",
        "price": 50,
        "quantity_requested": 1,
        "picture": ""
      }
    ]
  },
  {
    "id": "cc97b29a-1dbb-4f52-9f8a-e9a91266d63a",
    "creator_id": "",
    "name": "baby registry for Beatrice",
    "target_amount": 400,
    "total_raised": 388,
    "description": "",
    "thank_you_message": "",
    "category": "baby",
    "visibility": "",
    "cover_image": "",
    "createdAt": "",
    "updatedAt": "",
    "archived": false,
    "deleted": false,
    "items": [
      {
        "id": "71",
        "name": "soft swaddle blankets and sleep sacks ",
        "description": "",
        "price": 50,
        "quantity_requested": 4,
        "picture": ""
      },
      {
        "id": "72",
        "name": "diaper bag",
        "description": "",
        "price": 100,
        "quantity_requested": 1,
        "picture": ""
      },
      {
        "id": "73",
        "name": "baby monitor ",
        "description": "",
        "price": 100,
        "quantity_requested": 1,
        "picture": ""
      }
    ]
  },
  {
    "id": "91f08de3-df66-4bae-b4ee-ffe163e13021",
    "creator_id": "",
    "name": "Hilda baby registry wishlist",
    "target_amount": 481.19,
    "total_raised": 190,
    "description": "",
    "thank_you_message": "",
    "category": "baby",
    "visibility": "",
    "cover_image": "",
    "createdAt": "",
    "updatedAt": "",
    "archived": false,
    "deleted": false,
    "items": [
      {
        "id": "74",
        "name": "toys",
        "description": "",
        "price": 50,
        "quantity_requested": 1,
        "picture": ""
      },
      {
        "id": "75",
        "name": "baby books",
        "description": "",
        "price": 50,
        "quantity_requested": 5,
        "picture": ""
      },
      {
        "id": "76",
        "name": "musical baby mobile",
        "description": "",
        "price": 100,
        "quantity_requested": 1,
        "picture": ""
      },
      {
        "id": "77",
        "name": "Personalized Gift for Family Custom Portraits Wall Decor",
        "description": "",
        "price": 36.1,
        "quantity_requested": 1,
        "picture": "https://res.cloudinary.com/drnmh0rkc/image/upload/v1741303213/popular%20items/ylngdm4qq5n6iyrmwru5.png"
      },
      {
        "id": "78",
        "name": "Personalized Mom Gift, Personalized Gift for Mom",
        "description": "",
        "price": 45.09,
        "quantity_requested": 1,
        "picture": "https://res.cloudinary.com/drnmh0rkc/image/upload/v1741303213/popular%20items/k872hpxrrzi4ywqbnndn.png"
      }
    ]
  },
  {
    "id": "1adcc29e-9505-4c51-a403-5c8bd0d43050",
    "creator_id": "",
    "name": "welcome for baby Mathew wishlist",
    "target_amount": 240.43,
    "total_raised": 200,
    "description": "",
    "thank_you_message": "",
    "category": "baby",
    "visibility": "",
    "cover_image": "",
    "createdAt": "",
    "updatedAt": "",
    "archived": false,
    "deleted": false,
    "items": [
      {
        "id": "79",
        "name": "Wall Nanny  Baby Gate Wall Protector",
        "description": "",
        "price": 19.95,
        "quantity_requested": 1,
        "picture": ""
      },
      {
        "id": "80",
        "name": "Soft Plush Fox Baby Blanket for Boys Girls Nursery Unisex",
        "description": "",
        "price": 21.99,
        "quantity_requested": 1,
        "picture": "https://res.cloudinary.com/drnmh0rkc/image/upload/v1741303211/popular%20items/lusddbk7inwkinrg454r.png"
      },
      {
        "id": "81",
        "name": "Personalized Gift for Family Custom Portraits Wall Decor",
        "description": "",
        "price": 36.1,
        "quantity_requested": 1,
        "picture": "https://res.cloudinary.com/drnmh0rkc/image/upload/v1741303213/popular%20items/ylngdm4qq5n6iyrmwru5.png"
      },
      {
        "id": "82",
        "name": "Personalized Baby Shower Gift Basket",
        "description": "",
        "price": 37.31,
        "quantity_requested": 1,
        "picture": "https://res.cloudinary.com/drnmh0rkc/image/upload/v1741303210/popular%20items/q8bmm8ymtg9usst10lov.png"
      },
      {
        "id": "83",
        "name": "Personalized Mom Gift, Personalized Gift for Mom",
        "description": "",
        "price": 45.09,
        "quantity_requested": 1,
        "picture": "https://res.cloudinary.com/drnmh0rkc/image/upload/v1741303213/popular%20items/k872hpxrrzi4ywqbnndn.png"
      },
      {
        "id": "84",
        "name": " Soother Toy",
        "description": "",
        "price": 79.99,
        "quantity_requested": 1,
        "picture": ""
      }
    ]
  },
  {
    "id": "5786f175-35a9-442c-9534-c7237f744f74",
    "creator_id": "",
    "name": "Road trip for honeymoon wishlist",
    "target_amount": 2000,
    "total_raised": 1780,
    "description": "",
    "thank_you_message": "",
    "category": "honeymoon",
    "visibility": "",
    "cover_image": "",
    "createdAt": "",
    "updatedAt": "",
    "archived": false,
    "deleted": false,
    "items": [
      {
        "id": "85",
        "name": "road trip",
        "description": "",
        "price": 2000,
        "quantity_requested": 1,
        "picture": ""
      }
    ]
  },
  {
    "id": "084de7d7-e632-4907-8b44-2571d903085a",
    "creator_id": "",
    "name": "Ashley & Rhoda wedding registry",
    "target_amount": 1400,
    "total_raised": 890,
    "description": "",
    "thank_you_message": "",
    "category": "wedding",
    "visibility": "",
    "cover_image": "",
    "createdAt": "",
    "updatedAt": "",
    "archived": false,
    "deleted": false,
    "items": [
      {
        "id": "86",
        "name": " Concert, Festival Tickets ",
        "description": "",
        "price": 200,
        "quantity_requested": 2,
        "picture": ""
      },
      {
        "id": "87",
        "name": "staycation",
        "description": "",
        "price": 1000,
        "quantity_requested": 1,
        "picture": ""
      }
    ]
  },
  {
    "id": "c82b563e-b062-49c0-bbe5-1f8801001a67",
    "creator_id": "",
    "name": "Trip to Taiwan for honeymoon wishlist",
    "target_amount": 4000,
    "total_raised": 2500,
    "description": "",
    "thank_you_message": "",
    "category": "honeymmon",
    "visibility": "",
    "cover_image": "",
    "createdAt": "",
    "updatedAt": "",
    "archived": false,
    "deleted": false,
    "items": [
      {
        "id": "88",
        "name": "travel to Taiwan",
        "description": "",
        "price": 2000,
        "quantity_requested": 2,
        "picture": ""
      }
    ]
  },
  {
    "id": "fd38ac2a-7de6-4d13-9837-6e1b75ffdc7c",
    "creator_id": "",
    "name": "new home welcome wishlist",
    "target_amount": 2300,
    "total_raised": 1090,
    "description": "",
    "thank_you_message": "",
    "category": "event",
    "visibility": "",
    "cover_image": "",
    "createdAt": "",
    "updatedAt": "",
    "archived": false,
    "deleted": false,
    "items": [
      {
        "id": "89",
        "name": "new paint and accent walls",
        "description": "",
        "price": 1000,
        "quantity_requested": 1,
        "picture": ""
      },
      {
        "id": "90",
        "name": "light fixtures",
        "description": "",
        "price": 300,
        "quantity_requested": 1,
        "picture": ""
      },
      {
        "id": "91",
        "name": "walking closet",
        "description": "",
        "price": 1000,
        "quantity_requested": 1,
        "picture": ""
      }
    ]
  },
  {
    "id": "393ea5c0-5617-4dd2-bd8e-5e79e27dad10",
    "creator_id": "",
    "name": "university freshman wishlist",
    "target_amount": 2428,
    "total_raised": 566,
    "description": "",
    "thank_you_message": "",
    "category": "event",
    "visibility": "",
    "cover_image": "",
    "createdAt": "",
    "updatedAt": "",
    "archived": false,
    "deleted": false,
    "items": [
      {
        "id": "92",
        "name": "macbook pro",
        "description": "",
        "price": 2099,
        "quantity_requested": 1,
        "picture": ""
      },
      {
        "id": "93",
        "name": "airpod pro",
        "description": "",
        "price": 329,
        "quantity_requested": 1,
        "picture": ""
      }
    ]
  },
  {
    "id": "8654c91a-920c-471b-a00d-43f66ddd7717",
    "creator_id": "",
    "name": "James birthday wishlist",
    "target_amount": 1000,
    "total_raised": 760,
    "description": "",
    "thank_you_message": "",
    "category": "event",
    "visibility": "",
    "cover_image": "",
    "createdAt": "",
    "updatedAt": "",
    "archived": false,
    "deleted": false,
    "items": [
      {
        "id": "1",
        "name": "Spanish classes",
        "description": "",
        "price": 1000,
        "quantity_requested": 1,
        "picture": ""
      }
    ]
  },
  {
    "id": "2470cee1-2c46-418e-844c-f0bf612ac1f5",
    "creator_id": "",
    "name": "Julia birthday wishlist",
    "target_amount": 500,
    "total_raised": 136,
    "description": "",
    "thank_you_message": "",
    "category": "event",
    "visibility": "",
    "cover_image": "",
    "createdAt": "",
    "updatedAt": "",
    "archived": false,
    "deleted": false,
    "items": [
      {
        "id": "2",
        "name": "Nintedo switch",
        "description": "",
        "price": 500,
        "quantity_requested": 1,
        "picture": ""
      }
    ]
  },
  {
    "id": "9793f907-0af9-4bea-b5ff-a3f9d907c444",
    "creator_id": "",
    "name": "Joe Baby registry wishlist",
    "target_amount": 1150,
    "total_raised": 240,
    "description": "",
    "thank_you_message": "",
    "category": "baby",
    "visibility": "",
    "cover_image": "",
    "createdAt": "",
    "updatedAt": "",
    "archived": false,
    "deleted": false,
    "items": [
      {
        "id": "3",
        "name": "Baby crib ",
        "description": "",
        "price": 300,
        "quantity_requested": 1,
        "picture": ""
      },
      {
        "id": "4",
        "name": "Stroller",
        "description": "",
        "price": 400,
        "quantity_requested": 1,
        "picture": ""
      },
      {
        "id": "5",
        "name": "Diaper fund",
        "description": "",
        "price": 200,
        "quantity_requested": 1,
        "picture": ""
      },
      {
        "id": "6",
        "name": "Baby monitor ",
        "description": "",
        "price": 150,
        "quantity_requested": 1,
        "picture": ""
      },
      {
        "id": "7",
        "name": "Baby clothes",
        "description": "",
        "price": 100,
        "quantity_requested": 1,
        "picture": ""
      }
    ]
  },
  {
    "id": "d3c92108-a78e-4373-829e-d664c76626f4",
    "creator_id": "",
    "name": "Frey baby registry wishlist",
    "target_amount": 284.99,
    "total_raised": 50,
    "description": "",
    "thank_you_message": "",
    "category": "baby",
    "visibility": "",
    "cover_image": "",
    "createdAt": "",
    "updatedAt": "",
    "archived": false,
    "deleted": false,
    "items": [
      {
        "id": "8",
        "name": "Organic food ",
        "description": "",
        "price": 100,
        "quantity_requested": 1,
        "picture": ""
      },
      {
        "id": "9",
        "name": "books ",
        "description": "",
        "price": 100,
        "quantity_requested": 1,
        "picture": ""
      },
      {
        "id": "10",
        "name": "Cloth diapers",
        "description": "",
        "price": 10,
        "quantity_requested": 5,
        "picture": ""
      },
      {
        "id": "11",
        "name": "Dr. Brown's Natural Flow Anti-Colic Options+ Narrow Baby Bottle, 4 pack",
        "description": "",
        "price": 34.99,
        "quantity_requested": 1,
        "picture": "https://res.cloudinary.com/drnmh0rkc/image/upload/v1741303212/popular%20items/toyxj9qfuszuzmjpx8g9.png"
      }
    ]
  },
  {
    "id": "bdc702b0-9701-4b24-8072-63859290b0c0",
    "creator_id": "",
    "name": "Amelia baby registry wishlist",
    "target_amount": 1050,
    "total_raised": 700,
    "description": "",
    "thank_you_message": "",
    "category": "baby",
    "visibility": "",
    "cover_image": "",
    "createdAt": "",
    "updatedAt": "",
    "archived": false,
    "deleted": false,
    "items": [
      {
        "id": "1",
        "name": "Baby skincare ",
        "description": "",
        "price": 100,
        "quantity_requested": 1,
        "picture": ""
      },
      {
        "id": "2",
        "name": "Baby blanket ",
        "description": "",
        "price": 50,
        "quantity_requested": 1,
        "picture": ""
      },
      {
        "id": "14",
        "name": "Car seat",
        "description": "",
        "price": 350,
        "quantity_requested": 1,
        "picture": ""
      },
      {
        "id": "15",
        "name": "Baby bathtub ",
        "description": "",
        "price": 50,
        "quantity_requested": 1,
        "picture": ""
      },
      {
        "id": "16",
        "name": "White noise machine ",
        "description": "",
        "price": 100,
        "quantity_requested": 1,
        "picture": ""
      },
      {
        "id": "17",
        "name": "Baby music class ",
        "description": "",
        "price": 100,
        "quantity_requested": 1,
        "picture": ""
      },
      {
        "id": "18",
        "name": "Anna first beach trip",
        "description": "",
        "price": 300,
        "quantity_requested": 1,
        "picture": ""
      }
    ]
  },
  {
    "id": "34658366-4524-4a95-9b31-f11dc6c559fd",
    "creator_id": "",
    "name": "Charlotte baby registry wishlist",
    "target_amount": 2600,
    "total_raised": 1080,
    "description": "",
    "thank_you_message": "",
    "category": "baby",
    "visibility": "",
    "cover_image": "",
    "createdAt": "",
    "updatedAt": "",
    "archived": false,
    "deleted": false,
    "items": [
      {
        "id": "19",
        "name": "Twin stroller",
        "description": "",
        "price": 600,
        "quantity_requested": 1,
        "picture": ""
      },
      {
        "id": "20",
        "name": "Two Cribs",
        "description": "",
        "price": 300,
        "quantity_requested": 2,
        "picture": ""
      },
      {
        "id": "21",
        "name": "Bottles and steriliser ",
        "description": "",
        "price": 200,
        "quantity_requested": 1,
        "picture": ""
      },
      {
        "id": "22",
        "name": "Clothes",
        "description": "",
        "price": 100,
        "quantity_requested": 2,
        "picture": ""
      },
      {
        "id": "23",
        "name": "Diaper ",
        "description": "",
        "price": 50,
        "quantity_requested": 20,
        "picture": ""
      }
    ]
  },
  {
    "id": "f9bff954-ea81-4e70-bcaf-2729e1902152",
    "creator_id": "",
    "name": "Emma & John wedding registry wihslist",
    "target_amount": 4400,
    "total_raised": 3000,
    "description": "",
    "thank_you_message": "",
    "category": "wedding",
    "visibility": "",
    "cover_image": "",
    "createdAt": "",
    "updatedAt": "",
    "archived": false,
    "deleted": false,
    "items": [
      {
        "id": "24",
        "name": "Honeymoon fund",
        "description": "",
        "price": 1000,
        "quantity_requested": 2,
        "picture": ""
      },
      {
        "id": "25",
        "name": "Dancing lesson ",
        "description": "",
        "price": 200,
        "quantity_requested": 2,
        "picture": ""
      },
      {
        "id": "26",
        "name": "Wedding photography ",
        "description": "",
        "price": 2000,
        "quantity_requested": 1,
        "picture": ""
      }
    ]
  },
  {
    "id": "95e9f30c-9ee0-46a4-9371-9799731d7fa9",
    "creator_id": "",
    "name": "Sophia & William wedding registy wihslist",
    "target_amount": 4850,
    "total_raised": 3000,
    "description": "",
    "thank_you_message": "",
    "category": "wedding",
    "visibility": "",
    "cover_image": "",
    "createdAt": "",
    "updatedAt": "",
    "archived": false,
    "deleted": false,
    "items": [
      {
        "id": "27",
        "name": "Maldives stay ",
        "description": "",
        "price": 1500,
        "quantity_requested": 2,
        "picture": ""
      },
      {
        "id": "28",
        "name": "Cooking class",
        "description": "",
        "price": 250,
        "quantity_requested": 1,
        "picture": ""
      },
      {
        "id": "29",
        "name": "Disney honeymoon pacakge",
        "description": "",
        "price": 300,
        "quantity_requested": 2,
        "picture": ""
      },
      {
        "id": "30",
        "name": "Ski resort ",
        "description": "",
        "price": 500,
        "quantity_requested": 2,
        "picture": ""
      }
    ]
  },
  {
    "id": "92e7b434-cc71-42ae-9054-1bd2176fcc18",
    "creator_id": "",
    "name": "Chloe & Lucas wedding registry wishlist",
    "target_amount": 3500,
    "total_raised": 1800,
    "description": "",
    "thank_you_message": "",
    "category": "wedding",
    "visibility": "",
    "cover_image": "",
    "createdAt": "",
    "updatedAt": "",
    "archived": false,
    "deleted": false,
    "items": [
      {
        "id": "31",
        "name": "Wedding flower ",
        "description": "",
        "price": 500,
        "quantity_requested": 1,
        "picture": ""
      },
      {
        "id": "32",
        "name": "Wedding videography ",
        "description": "",
        "price": 1500,
        "quantity_requested": 1,
        "picture": ""
      },
      {
        "id": "33",
        "name": "Live music ",
        "description": "",
        "price": 800,
        "quantity_requested": 1,
        "picture": ""
      },
      {
        "id": "34",
        "name": "Wedding cake ",
        "description": "",
        "price": 300,
        "quantity_requested": 1,
        "picture": ""
      },
      {
        "id": "35",
        "name": "Backyard wedding decor ",
        "description": "",
        "price": 400,
        "quantity_requested": 1,
        "picture": ""
      }
    ]
  },
  {
    "id": "a64e5f5f-e5ea-4f76-9436-b4bf9d0b123c",
    "creator_id": "",
    "name": "Mia & Oliver wedding registry wishlist",
    "target_amount": 8000,
    "total_raised": 5300,
    "description": "",
    "thank_you_message": "",
    "category": "wedding",
    "visibility": "",
    "cover_image": "",
    "createdAt": "",
    "updatedAt": "",
    "archived": false,
    "deleted": false,
    "items": [
      {
        "id": "36",
        "name": "Wedding fund ",
        "description": "",
        "price": 5000,
        "quantity_requested": 1,
        "picture": ""
      },
      {
        "id": "37",
        "name": "Honeymoon fund ",
        "description": "",
        "price": 1000,
        "quantity_requested": 2,
        "picture": ""
      },
      {
        "id": "38",
        "name": "Celebration fund ",
        "description": "",
        "price": 500,
        "quantity_requested": 2,
        "picture": ""
      }
    ]
  },
  {
    "id": "175a5cb6-6a2e-4239-a3c5-be522610cd5f",
    "creator_id": "",
    "name": "Olivia & Leo wedding registry wishlist",
    "target_amount": 4200,
    "total_raised": 1900,
    "description": "",
    "thank_you_message": "",
    "category": "wedding",
    "visibility": "",
    "cover_image": "",
    "createdAt": "",
    "updatedAt": "",
    "archived": false,
    "deleted": false,
    "items": [
      {
        "id": "39",
        "name": "Travel ",
        "description": "",
        "price": 500,
        "quantity_requested": 2,
        "picture": ""
      },
      {
        "id": "40",
        "name": "Hotel stay",
        "description": "",
        "price": 1000,
        "quantity_requested": 1,
        "picture": ""
      },
      {
        "id": "41",
        "name": "Professional photos",
        "description": "",
        "price": 2000,
        "quantity_requested": 1,
        "picture": ""
      },
      {
        "id": "42",
        "name": "Surprise gifts ",
        "description": "",
        "price": 100,
        "quantity_requested": 2,
        "picture": ""
      }
    ]
  },
  {
    "id": "d10a2b05-344a-43c4-9d8d-d3dc14d91953",
    "creator_id": "",
    "name": "Margot & Zayn wedding wishlist",
    "target_amount": 5250,
    "total_raised": 600,
    "description": "",
    "thank_you_message": "",
    "category": "wedding",
    "visibility": "",
    "cover_image": "",
    "createdAt": "",
    "updatedAt": "",
    "archived": false,
    "deleted": false,
    "items": [
      {
        "id": "45",
        "name": "Wedding place rental ",
        "description": "",
        "price": 5000,
        "quantity_requested": 1,
        "picture": ""
      },
      {
        "id": "46",
        "name": "Rings",
        "description": "",
        "price": 250,
        "quantity_requested": 2,
        "picture": ""
      }
    ]
  },
  {
    "id": "8a3a8323-eca9-4273-a13d-8d94532ce2d8",
    "creator_id": "",
    "name": "Evelyn & Ezra wedding registry wishlist",
    "target_amount": 1000,
    "total_raised": 450,
    "description": "",
    "thank_you_message": "",
    "category": "wedding",
    "visibility": "",
    "cover_image": "",
    "createdAt": "",
    "updatedAt": "",
    "archived": false,
    "deleted": false,
    "items": [
      {
        "id": "47",
        "name": "Decoration ",
        "description": "",
        "price": 300,
        "quantity_requested": 1,
        "picture": ""
      },
      {
        "id": "48",
        "name": "Hand made Wedding cake ",
        "description": "",
        "price": 200,
        "quantity_requested": 1,
        "picture": ""
      },
      {
        "id": "49",
        "name": "DIY wedding playlist",
        "description": "",
        "price": 100,
        "quantity_requested": 1,
        "picture": ""
      },
      {
        "id": "50",
        "name": "Friends officiated ceremony ",
        "description": "",
        "price": 200,
        "quantity_requested": 1,
        "picture": ""
      },
      {
        "id": "51",
        "name": "Guest taken photos",
        "description": "",
        "price": 200,
        "quantity_requested": 1,
        "picture": ""
      }
    ]
  },
  {
    "id": "2896ce60-e201-418a-965a-0f4a50656bfa",
    "creator_id": "",
    "name": "Isabeth & Jack Wedding registry wishlist",
    "target_amount": 4500,
    "total_raised": 800,
    "description": "",
    "thank_you_message": "",
    "category": "wedding",
    "visibility": "",
    "cover_image": "",
    "createdAt": "",
    "updatedAt": "",
    "archived": false,
    "deleted": false,
    "items": [
      {
        "id": "52",
        "name": "Live orchestra ",
        "description": "",
        "price": 2000,
        "quantity_requested": 1,
        "picture": ""
      },
      {
        "id": "53",
        "name": "Fireworks and champagne toast ",
        "description": "",
        "price": 2500,
        "quantity_requested": 1,
        "picture": ""
      }
    ]
  },
  {
    "id": "90dbc7b4-60d6-4a35-9d23-0a880924565f",
    "creator_id": "",
    "name": "Elijah & Ava wedding registry wishlist",
    "target_amount": 5700,
    "total_raised": 2000,
    "description": "",
    "thank_you_message": "",
    "category": "wedding",
    "visibility": "",
    "cover_image": "",
    "createdAt": "",
    "updatedAt": "",
    "archived": false,
    "deleted": false,
    "items": [
      {
        "id": "54",
        "name": "Live string quartet ",
        "description": "",
        "price": 1000,
        "quantity_requested": 1,
        "picture": ""
      },
      {
        "id": "55",
        "name": "Wedding DJ",
        "description": "",
        "price": 1500,
        "quantity_requested": 1,
        "picture": ""
      },
      {
        "id": "56",
        "name": "Photo Booth ",
        "description": "",
        "price": 700,
        "quantity_requested": 1,
        "picture": ""
      },
      {
        "id": "57",
        "name": "Fireworks ",
        "description": "",
        "price": 2000,
        "quantity_requested": 1,
        "picture": ""
      },
      {
        "id": "58",
        "name": "Champagne tower ",
        "description": "",
        "price": 500,
        "quantity_requested": 1,
        "picture": ""
      }
    ]
  }
]
